CHANGES.rst
LICENSE
MANIFEST.in
README
README.rst
requirements.txt
setup.py
envconf/__init__.py
envconf.egg-info/PKG-INFO
envconf.egg-info/SOURCES.txt
envconf.egg-info/dependency_links.txt
envconf.egg-info/top_level.txt