Metadata-Version: 1.1
Name: envconf
Version: 0.1.0
Summary: An unique way to manage your configuration
Home-page: https://github.com/bfontaine/envconf
Author: Baptiste Fontaine
Author-email: b@ptistefontaine.fr
License: Copyright © 2014 – Baptiste Fontaine
